calocem/__init__.py
calocem/analysis.py
calocem/data_processing.py
calocem/exceptions.py
calocem/file_io.py
calocem/measurement.py
calocem/plotting.py
calocem/processparams.py
calocem/tacalorimetry.py
calocem/utils.py
calocem/DATA/Reference_interpolated.csv
calocem/DATA/c3a.csv
calocem/DATA/calorimetry_data_1.csv
calocem/DATA/calorimetry_data_2.csv
calocem/DATA/calorimetry_data_3.csv
calocem/DATA/calorimetry_data_4.csv
calocem/DATA/calorimetry_data_5.csv
calocem/DATA/calorimetry_data_6.csv
calocem/DATA/corrupt_example.csv
calocem/DATA/downsample1.csv
calocem/DATA/excel_example2.xls
calocem/DATA/excel_example3.xls
calocem/DATA/excel_example4.xls
calocem/DATA/gen1_calofile.csv
calocem/DATA/gen1_calofile2.csv
calocem/DATA/gen1_calofile3.csv
calocem/DATA/gen3_calofile.csv
calocem/DATA/gen3_calofile_no_mass.csv
calocem/DATA/insitu_bm.csv
calocem/DATA/insitu_bm2.csv
calocem/DATA/peak_detection_example1.csv
calocem/DATA/peak_detection_example2.csv
calocem/DATA/peak_detection_example3.csv
calocem/DATA/peak_detection_example4.csv
calocem/DATA/peak_detection_example5.csv
calocem/DATA/peak_detection_example7.csv
calocem/DATA/peak_detection_noise_example.csv
calocem/DATA/peak_detection_noise_example2.csv
calocem/DATA/peak_detection_noise_example3.csv
calocem/DATA/peak_detection_noise_example4.csv
calocem/DATA/processed_data.csv
calocem/DATA/processed_data_2.csv
calocem/DATA/processed_data_3.csv
calocem-0.2.4.dist-info/METADATA
calocem-0.2.4.dist-info/WHEEL
calocem-0.2.4.dist-info/licenses/LICENSE
calocem-0.2.4.dist-info/RECORD
