Metadata-Version: 2.4
Name: CaloCem
Version: 0.2.4
Summary: Handling TAM Air calorimetry files made easy.
Project-URL: Repository, https://github.com/mj-hofmann/CaloCem
Project-URL: Documentation, https://mj-hofmann.github.io/CaloCem/
Author-email: mj-hofmann <aCodingChemist@gmail.com>, tgaedt <torben.gaedt@tum.de>
License-Expression: MIT
License-File: LICENSE
Keywords: TA Instruments,TAM Air,analysis,calorimetry,vizualisation
Requires-Python: <4,>=3.10.1
Requires-Dist: matplotlib<4,>=3.9.1
Requires-Dist: mypy<0.992,>=0.991
Requires-Dist: numpy<3,>=2.1.1
Requires-Dist: openpyxl>=3.1.5
Requires-Dist: pandas<3,>=2.1.1
Requires-Dist: pysnooper<2,>=1.1.1
Requires-Dist: pytest-cov>=4.0.0
Requires-Dist: pytest>=7.2.0
Requires-Dist: requests<3,>=2.28.1
Requires-Dist: scipy<2,>=1.14.1
Requires-Dist: xlrd<3,>=2.0.1
